LICENSE
MANIFEST.in
README.md
setup.py
tap_youtube_analytics/__init__.py
tap_youtube_analytics/client.py
tap_youtube_analytics/dim_lookup_map.json
tap_youtube_analytics/discover.py
tap_youtube_analytics/schema.py
tap_youtube_analytics/streams.py
tap_youtube_analytics/sync.py
tap_youtube_analytics/transform.py
tap_youtube_analytics.egg-info/PKG-INFO
tap_youtube_analytics.egg-info/SOURCES.txt
tap_youtube_analytics.egg-info/dependency_links.txt
tap_youtube_analytics.egg-info/entry_points.txt
tap_youtube_analytics.egg-info/requires.txt
tap_youtube_analytics.egg-info/top_level.txt
tap_youtube_analytics/schemas/_schema_template.json
tap_youtube_analytics/schemas/channels.json
tap_youtube_analytics/schemas/playlist_items.json
tap_youtube_analytics/schemas/playlists.json
tap_youtube_analytics/schemas/reports.json
tap_youtube_analytics/schemas/videos.json