Metadata-Version: 2.1
Name: tap-youtube-analytics
Version: 0.0.9
Summary: Singer.io tap for extracting data from the Google Search Console API
Home-page: UNKNOWN
Author: jeff.huth@bytecode.io
License: UNKNOWN
Platform: UNKNOWN
Classifier: Programming Language :: Python :: 3 :: Only
Provides-Extra: dev
